MANIFEST.in
README.md
requirements.txt
setup.py
mindsdb_sdk/__about__.py
mindsdb_sdk/__init__.py
mindsdb_sdk/classes/__init__.py
mindsdb_sdk/classes/authorizers.py
mindsdb_sdk/classes/config.py
mindsdb_sdk/classes/datasources.py
mindsdb_sdk/classes/intergrations.py
mindsdb_sdk/classes/pandas_acessor.py
mindsdb_sdk/classes/predictors.py
mindsdb_sdk/classes/proxy.py
mindsdb_sdk/classes/sdk.py
mindsdb_sdk/helpers/__init__.py
mindsdb_sdk/helpers/exceptions.py
mindsdb_sdk/helpers/net_helpers.py
pd_auto_ml.egg-info/PKG-INFO
pd_auto_ml.egg-info/SOURCES.txt
pd_auto_ml.egg-info/dependency_links.txt
pd_auto_ml.egg-info/requires.txt
pd_auto_ml.egg-info/top_level.txt