Metadata-Version: 2.1
Name: pd-auto-ml
Version: 0.5.0
Summary: Pd auto_ml provides a pandas dataframe accessor to allow using dataframes with MindsDB (either the local native library or a local or remote mindsdb server)
Home-page: https://github.com/mindsdb/mindsdb_python_sdk
Author: MindsDB Inc
Author-email: jorge@mindsdb.com
License: GPL-3.0
Download-URL: https://pypi.org/project/pd_auto_ml/
Platform: UNKNOWN
Classifier: Programming Language :: Python :: 3
Classifier: License :: OSI Approved :: MIT License
Classifier: Operating System :: OS Independent
Requires-Python: >=3.6
